{
  "kind": "class",
  "description": "`furo-ui5-typerenderer-labeled`\nThe furo-ui5-typerenderer-labeled is a composition to easily use a display field with label according\nto the design specification of SAP Fiori Design System.",
  "name": "FuroUi5TyperendererLabeled",
  "members": [
    {
      "kind": "method",
      "name": "_FBPReady",
      "description": "flow is ready lifecycle method",
      "privacy": "private"
    },
    {
      "kind": "method",
      "name": "bindData",
      "parameters": [
        {
          "name": "fieldNode",
          "type": {
            "text": "FieldNode"
          }
        }
      ],
      "description": "Binds the fieldNode to the component\nbinding set can be customised here otherwise the standard bindData in the ui5-data-input will be used"
    },
    {
      "kind": "field",
      "name": "label",
      "type": {
        "text": "string"
      },
      "default": "''",
      "privacy": "public",
      "description": "the label for the data-text-input",
      "attribute": "label"
    },
    {
      "kind": "field",
      "name": "valueState",
      "type": {
        "text": "string"
      },
      "default": "''",
      "privacy": "public",
      "description": "Value State",
      "attribute": "value-state",
      "reflects": true
    },
    {
      "kind": "field",
      "name": "context",
      "type": {
        "text": "string"
      },
      "default": "'display'",
      "privacy": "public",
      "attribute": "context"
    },
    {
      "kind": "field",
      "name": "disabled",
      "privacy": "public",
      "description": "Disabled State",
      "attribute": "disabled",
      "reflects": true
    }
  ],
  "attributes": [
    {
      "name": "label",
      "description": "the label for the data-text-input",
      "fieldName": "label"
    },
    {
      "name": "value-state",
      "description": "Value State",
      "fieldName": "valueState"
    },
    {
      "name": "disabled",
      "description": "Disabled State",
      "fieldName": "disabled"
    },
    {
      "name": "context",
      "fieldName": "context"
    }
  ],
  "mixins": [
    {
      "name": "FBP",
      "package": "@furo/fbp/src/fbp.js"
    }
  ],
  "superclass": {
    "name": "LitElement",
    "package": "lit"
  },
  "summary": "labeled input field",
  "tagName": "furo-ui5-typerenderer-labeled",
  "customElement": true
}
